mybody_api_client/__init__.py
mybody_api_client/sections/__init__.py
mybody_api_client/sections/account.py
mybody_api_client/sections/article.py
mybody_api_client/sections/base.py
mybody_api_client/sections/country.py
mybody_api_client/sections/currency.py
mybody_api_client/sections/language.py
mybody_api_client/sections/notification_service.py
mybody_api_client/sections/role.py
mybody_api_client/sections/service.py
mybody_api_client/sections/session.py
mybody_api_client/sections/text.py
mybody_api_client/sections/timezone.py
mybody_api_client-0.3.1.dist-info/LICENSE
mybody_api_client-0.3.1.dist-info/METADATA
mybody_api_client-0.3.1.dist-info/WHEEL
mybody_api_client-0.3.1.dist-info/top_level.txt
mybody_api_client-0.3.1.dist-info/RECORD
